.gitlab-ci.yml
.travis.yml
CHANGES.rst
CONTRIBUTORS.rst
DEVELOP.rst
LICENSE.GPL
LICENSE.rst
MANIFEST.in
README.rst
requirements.txt
setup.cfg
setup.py
docs/index.rst
src/collective/__init__.py
src/collective.fgrcon.pgeasyform.egg-info/PKG-INFO
src/collective.fgrcon.pgeasyform.egg-info/SOURCES.txt
src/collective.fgrcon.pgeasyform.egg-info/dependency_links.txt
src/collective.fgrcon.pgeasyform.egg-info/entry_points.txt
src/collective.fgrcon.pgeasyform.egg-info/namespace_packages.txt
src/collective.fgrcon.pgeasyform.egg-info/not-zip-safe
src/collective.fgrcon.pgeasyform.egg-info/requires.txt
src/collective.fgrcon.pgeasyform.egg-info/top_level.txt
src/collective/fgrcon/__init__.py
src/collective/fgrcon/pgeasyform/__init__.py
src/collective/fgrcon/pgeasyform/actions.py
src/collective/fgrcon/pgeasyform/actions.zcml
src/collective/fgrcon/pgeasyform/configure.zcml
src/collective/fgrcon/pgeasyform/interfaces.py
src/collective/fgrcon/pgeasyform/permissions.zcml
src/collective/fgrcon/pgeasyform/setuphandlers.py
src/collective/fgrcon/pgeasyform/testing.py
src/collective/fgrcon/pgeasyform/upgrades.py
src/collective/fgrcon/pgeasyform/upgrades.zcml
src/collective/fgrcon/pgeasyform/locales/README.rst
src/collective/fgrcon/pgeasyform/locales/__init__.py
src/collective/fgrcon/pgeasyform/locales/collective.fgrcon.pgeasyform.pot
src/collective/fgrcon/pgeasyform/locales/update.py
src/collective/fgrcon/pgeasyform/locales/update.sh
src/collective/fgrcon/pgeasyform/locales/en/LC_MESSAGES/collective.fgrcon.pgeasyform.mo
src/collective/fgrcon/pgeasyform/locales/en/LC_MESSAGES/collective.fgrcon.pgeasyform.po
src/collective/fgrcon/pgeasyform/profiles/default/browserlayer.xml
src/collective/fgrcon/pgeasyform/profiles/default/metadata.xml
src/collective/fgrcon/pgeasyform/profiles/uninstall/browserlayer.xml
src/collective/fgrcon/pgeasyform/tests/__init__.py
src/collective/fgrcon/pgeasyform/tests/test_robot.py
src/collective/fgrcon/pgeasyform/tests/test_setup.py
src/collective/fgrcon/pgeasyform/tests/robot/test_example.robot