Metadata-Version: 2.1
Name: collective.fgrcon.pgeasyform
Version: 1.1
Summary: Extend collective.easyform with a handler for Postgresql
Home-page: https://pypi.python.org/pypi/collective.fgrcon.pgeasyform
Author: Franz Gerhard Reinisch
Author-email: franz@fgrcon.net
License: GPL version 2
Keywords: Python Plone
Platform: UNKNOWN
Classifier: Environment :: Web Environment
Classifier: Framework :: Plone
Classifier: Framework :: Plone :: 5.1
Classifier: Framework :: Plone :: 5.2
Classifier: Programming Language :: Python
Classifier: Programming Language :: Python :: 2.7
Classifier: Programming Language :: Python :: 3.6
Classifier: Operating System :: OS Independent
Classifier: License :: OSI Approved :: GNU General Public License v2 (GPLv2)
Provides-Extra: test
